[
  {
    "id": "COL.3.1",
    "book": "Colossians",
    "bookNum": 51,
    "bookAbbrev": "COL",
    "chapter": 3,
    "verse": 1,
    "text": "If ye then be risen with Christ, seek those things which are above, where Christ sitteth on the right hand of God.",
    "hash": "8325bc3b57377c51960b74625dbe8bf0d0c45adbed0adfffe88795c681187ce5"
  },
  {
    "id": "COL.3.2",
    "book": "Colossians",
    "bookNum": 51,
    "bookAbbrev": "COL",
    "chapter": 3,
    "verse": 2,
    "text": "Set your affection on things above, not on things on the earth. {affection: or, mind}",
    "hash": "25ddbebd620d3f402305974af16d2509985132b12cefbcf261a8f24ca2d16482"
  },
  {
    "id": "COL.3.3",
    "book": "Colossians",
    "bookNum": 51,
    "bookAbbrev": "COL",
    "chapter": 3,
    "verse": 3,
    "text": "For ye are dead, and your life is hid with Christ in God.",
    "hash": "0fd7298f7835330ae385d829482a1af14e6838adacbfe88f6b3e287e07a2bf17"
  },
  {
    "id": "COL.3.4",
    "book": "Colossians",
    "bookNum": 51,
    "bookAbbrev": "COL",
    "chapter": 3,
    "verse": 4,
    "text": "When Christ, {who is} our life, shall appear, then shall ye also appear with him in glory.",
    "hash": "01e748470da1a2e940d0d44cc83cfa84a93eae0af605423360ffafc56add0118"
  },
  {
    "id": "COL.3.5",
    "book": "Colossians",
    "bookNum": 51,
    "bookAbbrev": "COL",
    "chapter": 3,
    "verse": 5,
    "text": "Mortify therefore your members which are upon the earth; fornication, uncleanness, inordinate affection, evil concupiscence, and covetousness, which is idolatry:",
    "hash": "b76cfdc46301c305e71d4d7da400c8526528f99ac558a437ed223accd6cf7162"
  },
  {
    "id": "COL.3.6",
    "book": "Colossians",
    "bookNum": 51,
    "bookAbbrev": "COL",
    "chapter": 3,
    "verse": 6,
    "text": "For which things' sake the wrath of God cometh on the children of disobedience:",
    "hash": "141c4b2b4cbf0a6a5156f99e97577e6e1041cf7f191e9371226e313cd186dd0f"
  },
  {
    "id": "COL.3.7",
    "book": "Colossians",
    "bookNum": 51,
    "bookAbbrev": "COL",
    "chapter": 3,
    "verse": 7,
    "text": "In the which ye also walked some time, when ye lived in them.",
    "hash": "632890ffd757a01f20a7b30aaf36cde9f6d4cb333147e1b6658dec459bdab32b"
  },
  {
    "id": "COL.3.8",
    "book": "Colossians",
    "bookNum": 51,
    "bookAbbrev": "COL",
    "chapter": 3,
    "verse": 8,
    "text": "But now ye also put off all these; anger, wrath, malice, blasphemy, filthy communication out of your mouth.",
    "hash": "ad3336d6533afa8d24e0c0602457fccab5423342cac72613a83789962c5f7cd9"
  },
  {
    "id": "COL.3.9",
    "book": "Colossians",
    "bookNum": 51,
    "bookAbbrev": "COL",
    "chapter": 3,
    "verse": 9,
    "text": "Lie not one to another, seeing that ye have put off the old man with his deeds;",
    "hash": "3a7453daa6ee9b11293b54b20d675a49a85a84da971a6ff606fbd2c314dd76b6"
  },
  {
    "id": "COL.3.10",
    "book": "Colossians",
    "bookNum": 51,
    "bookAbbrev": "COL",
    "chapter": 3,
    "verse": 10,
    "text": "And have put on the new {man}, which is renewed in knowledge after the image of him that created him:",
    "hash": "eb1356ace367f7eb177ed62b87b7ba60cda8850370fa1d1540290199ad5b47fc"
  },
  {
    "id": "COL.3.11",
    "book": "Colossians",
    "bookNum": 51,
    "bookAbbrev": "COL",
    "chapter": 3,
    "verse": 11,
    "text": "Where there is neither Greek nor Jew, circumcision nor uncircumcision, Barbarian, Scythian, bond {nor} free: but Christ {is} all, and in all.",
    "hash": "f53ba20f8794f7935b7eda1dfe1756a3fed164c83415d38cd02db778af231cfb"
  },
  {
    "id": "COL.3.12",
    "book": "Colossians",
    "bookNum": 51,
    "bookAbbrev": "COL",
    "chapter": 3,
    "verse": 12,
    "text": "Put on therefore, as the elect of God, holy and beloved, bowels of mercies, kindness, humbleness of mind, meekness, longsuffering;",
    "hash": "e292f3fdfa325453aec8376f7becf27a12fb26f977c36bc0f8c9d0b34c3638f2"
  },
  {
    "id": "COL.3.13",
    "book": "Colossians",
    "bookNum": 51,
    "bookAbbrev": "COL",
    "chapter": 3,
    "verse": 13,
    "text": "Forbearing one another, and forgiving one another, if any man have a quarrel against any: even as Christ forgave you, so also {do} ye. {quarrel: or, complaint}",
    "hash": "2481eacc6144355e5fb8e60135a15b06cd47f67338120804b03b991a344573bc"
  },
  {
    "id": "COL.3.14",
    "book": "Colossians",
    "bookNum": 51,
    "bookAbbrev": "COL",
    "chapter": 3,
    "verse": 14,
    "text": "And above all these things {put on} charity, which is the bond of perfectness.",
    "hash": "f3e287ed624757124ea8b77570dcc10a365d714ccb454cf6432217f737ba96ac"
  },
  {
    "id": "COL.3.15",
    "book": "Colossians",
    "bookNum": 51,
    "bookAbbrev": "COL",
    "chapter": 3,
    "verse": 15,
    "text": "And let the peace of God rule in your hearts, to the which also ye are called in one body; and be ye thankful.",
    "hash": "96ccbb898f01d8fd4035b8fbb56d5026f3fabaf38d1bd1ddfc59a404d8e24428"
  },
  {
    "id": "COL.3.16",
    "book": "Colossians",
    "bookNum": 51,
    "bookAbbrev": "COL",
    "chapter": 3,
    "verse": 16,
    "text": "Let the word of Christ dwell in you richly in all wisdom; teaching and admonishing one another in psalms and hymns and spiritual songs, singing with grace in your hearts to the Lord.",
    "hash": "ee17cef3d29afd60b2e3e5e01136989c5fad265ef79cd8dd99111f5978eee25b"
  },
  {
    "id": "COL.3.17",
    "book": "Colossians",
    "bookNum": 51,
    "bookAbbrev": "COL",
    "chapter": 3,
    "verse": 17,
    "text": "And whatsoever ye do in word or deed, {do} all in the name of the Lord Jesus, giving thanks to God and the Father by him.",
    "hash": "c16efa736b873ee0737983f13787a91bbf9012a40586a0082cfc7350677d68c1"
  },
  {
    "id": "COL.3.18",
    "book": "Colossians",
    "bookNum": 51,
    "bookAbbrev": "COL",
    "chapter": 3,
    "verse": 18,
    "text": "Wives, submit yourselves unto your own husbands, as it is fit in the Lord.",
    "hash": "60b99814c1d701e49f3fcd551352479160af6485e4a3fb1afaad1c493dbd7302"
  },
  {
    "id": "COL.3.19",
    "book": "Colossians",
    "bookNum": 51,
    "bookAbbrev": "COL",
    "chapter": 3,
    "verse": 19,
    "text": "Husbands, love {your} wives, and be not bitter against them.",
    "hash": "5be9133f98dbfe27309de3a0cf54974ba3931759357ddff0df6c1a5b6912123c"
  },
  {
    "id": "COL.3.20",
    "book": "Colossians",
    "bookNum": 51,
    "bookAbbrev": "COL",
    "chapter": 3,
    "verse": 20,
    "text": "Children, obey {your} parents in all things: for this is well pleasing unto the Lord.",
    "hash": "66208a143cec6769e0e11171c331c0e0f53624ec3ce71c814d3a861c2f21205a"
  },
  {
    "id": "COL.3.21",
    "book": "Colossians",
    "bookNum": 51,
    "bookAbbrev": "COL",
    "chapter": 3,
    "verse": 21,
    "text": "Fathers, provoke not your children {to anger}, lest they be discouraged.",
    "hash": "1dee745a933c53fd0522f60a040ac09796a48d48c23ac3c9c6ebe55ff75fd9bf"
  },
  {
    "id": "COL.3.22",
    "book": "Colossians",
    "bookNum": 51,
    "bookAbbrev": "COL",
    "chapter": 3,
    "verse": 22,
    "text": "Servants, obey in all things {your} masters according to the flesh; not with eyeservice, as menpleasers; but in singleness of heart, fearing God:",
    "hash": "5245198fc9d187502d6152b212c344f10cce957f7bf7a5739e3bccafff3d8114"
  },
  {
    "id": "COL.3.23",
    "book": "Colossians",
    "bookNum": 51,
    "bookAbbrev": "COL",
    "chapter": 3,
    "verse": 23,
    "text": "And whatsoever ye do, do {it} heartily, as to the Lord, and not unto men;",
    "hash": "0455aad27012d3430df95319ca89218bc712c5758c087ee64ac9189a3bc3a16c"
  },
  {
    "id": "COL.3.24",
    "book": "Colossians",
    "bookNum": 51,
    "bookAbbrev": "COL",
    "chapter": 3,
    "verse": 24,
    "text": "Knowing that of the Lord ye shall receive the reward of the inheritance: for ye serve the Lord Christ.",
    "hash": "2a508912a72b44472c35543c6b28d3b47843cf9a0981f632a01e6a1756a95db9"
  },
  {
    "id": "COL.3.25",
    "book": "Colossians",
    "bookNum": 51,
    "bookAbbrev": "COL",
    "chapter": 3,
    "verse": 25,
    "text": "But he that doeth wrong shall receive for the wrong which he hath done: and there is no respect of persons.",
    "hash": "e0aa126a0fc6afe8acf579634e884b82b7b9810aa178096967243d2be84a20c7"
  }
]