[
  {
    "id": "PSA.63.1",
    "book": "Psalms",
    "bookNum": 19,
    "bookAbbrev": "PSA",
    "chapter": 63,
    "verse": 1,
    "text": "[A Psalm of David, when he was in the wilderness of Judah.] O God, thou {art} my God; early will I seek thee: my soul thirsteth for thee, my flesh longeth for thee in a dry and thirsty land, where no water is; {thirsty: Heb. weary} {where...: without water}",
    "hash": "09e2a58e6b4290030d1dd992d444b09a6baf2c1c8774debdd064796ab71cdd18"
  },
  {
    "id": "PSA.63.2",
    "book": "Psalms",
    "bookNum": 19,
    "bookAbbrev": "PSA",
    "chapter": 63,
    "verse": 2,
    "text": "To see thy power and thy glory, so {as} I have seen thee in the sanctuary.",
    "hash": "7de85cda547c83b268d8ef117bbf14a2c053ac9ea511a66c0d62208a4b6407b1"
  },
  {
    "id": "PSA.63.3",
    "book": "Psalms",
    "bookNum": 19,
    "bookAbbrev": "PSA",
    "chapter": 63,
    "verse": 3,
    "text": "Because thy lovingkindness {is} better than life, my lips shall praise thee.",
    "hash": "09c304fc09b93a7c2024f02720b73bb251a44870ab6f406d9fe115bba86f80ad"
  },
  {
    "id": "PSA.63.4",
    "book": "Psalms",
    "bookNum": 19,
    "bookAbbrev": "PSA",
    "chapter": 63,
    "verse": 4,
    "text": "Thus will I bless thee while I live: I will lift up my hands in thy name.",
    "hash": "ccdcc3b988397e7974a44272c5d763c13fc722e765a9b71d9fcade1290b02577"
  },
  {
    "id": "PSA.63.5",
    "book": "Psalms",
    "bookNum": 19,
    "bookAbbrev": "PSA",
    "chapter": 63,
    "verse": 5,
    "text": "My soul shall be satisfied as {with} marrow and fatness; and my mouth shall praise {thee} with joyful lips: {marrow: Heb. fatness}",
    "hash": "7d5de234e0c1e080ec0eafb0c35fe16c03c9c23fd67370f4eecfc9e0a1616a9b"
  },
  {
    "id": "PSA.63.6",
    "book": "Psalms",
    "bookNum": 19,
    "bookAbbrev": "PSA",
    "chapter": 63,
    "verse": 6,
    "text": "When I remember thee upon my bed, {and} meditate on thee in the {night} watches.",
    "hash": "32b94e508deaf168421a33918b291236d01816a19dddf961f67327061f9eb0f5"
  },
  {
    "id": "PSA.63.7",
    "book": "Psalms",
    "bookNum": 19,
    "bookAbbrev": "PSA",
    "chapter": 63,
    "verse": 7,
    "text": "Because thou hast been my help, therefore in the shadow of thy wings will I rejoice.",
    "hash": "6abb7d71340e4778a7c5a28f7222e38d3939f0c1c2e4c1e088859d8289521f5a"
  },
  {
    "id": "PSA.63.8",
    "book": "Psalms",
    "bookNum": 19,
    "bookAbbrev": "PSA",
    "chapter": 63,
    "verse": 8,
    "text": "My soul followeth hard after thee: thy right hand upholdeth me.",
    "hash": "800612554e883cc3db0c54bef61ac54c15cf5fa61b3f9261f395f025050e9b36"
  },
  {
    "id": "PSA.63.9",
    "book": "Psalms",
    "bookNum": 19,
    "bookAbbrev": "PSA",
    "chapter": 63,
    "verse": 9,
    "text": "But those {that} seek my soul, to destroy {it}, shall go into the lower parts of the earth.",
    "hash": "c529e84bea9e98056106fa4bc1711286eac2e6c7db5f975f602d4ca4fc6aafa0"
  },
  {
    "id": "PSA.63.10",
    "book": "Psalms",
    "bookNum": 19,
    "bookAbbrev": "PSA",
    "chapter": 63,
    "verse": 10,
    "text": "They shall fall by the sword: they shall be a portion for foxes. {They shall fall...: Heb. They shall make him run out like water by the hands of}",
    "hash": "f1098011028de2a782d1c71d41f41ed9baad4256865c4d26855274c7c80e0424"
  },
  {
    "id": "PSA.63.11",
    "book": "Psalms",
    "bookNum": 19,
    "bookAbbrev": "PSA",
    "chapter": 63,
    "verse": 11,
    "text": "But the king shall rejoice in God; every one that sweareth by him shall glory: but the mouth of them that speak lies shall be stopped.",
    "hash": "4204dc8e8c34457aeff24125c11f6a2381d039c9f1a8e281f0f72d9754a4e86a"
  }
]