[
  {
    "id": "PSA.21.1",
    "book": "Psalms",
    "bookNum": 19,
    "bookAbbrev": "PSA",
    "chapter": 21,
    "verse": 1,
    "text": "[To the chief Musician, A Psalm of David.] The king shall joy in thy strength, O LORD; and in thy salvation how greatly shall he rejoice!",
    "hash": "352db02c98ea98e5e21667dc2823a7cca3d59658f174afbeecee32fbb7ca7aa9"
  },
  {
    "id": "PSA.21.2",
    "book": "Psalms",
    "bookNum": 19,
    "bookAbbrev": "PSA",
    "chapter": 21,
    "verse": 2,
    "text": "Thou hast given him his heart's desire, and hast not withholden the request of his lips. Selah.",
    "hash": "3463a50fd9c770101dd7a3ce22ecfe985f6509d51752f61528275b0b853e7e62"
  },
  {
    "id": "PSA.21.3",
    "book": "Psalms",
    "bookNum": 19,
    "bookAbbrev": "PSA",
    "chapter": 21,
    "verse": 3,
    "text": "For thou preventest him with the blessings of goodness: thou settest a crown of pure gold on his head.",
    "hash": "92c3d9d5e7013df754a3f47eb01f3d66feeba0bf0ed6e5d4dbe841d4efd0e38c"
  },
  {
    "id": "PSA.21.4",
    "book": "Psalms",
    "bookNum": 19,
    "bookAbbrev": "PSA",
    "chapter": 21,
    "verse": 4,
    "text": "He asked life of thee, {and} thou gavest {it} him, {even} length of days for ever and ever.",
    "hash": "e4edea6ea0e612c356fb2cd6e662f46ee621313cb6ecb29850d79e0a0eabc18b"
  },
  {
    "id": "PSA.21.5",
    "book": "Psalms",
    "bookNum": 19,
    "bookAbbrev": "PSA",
    "chapter": 21,
    "verse": 5,
    "text": "His glory {is} great in thy salvation: honour and majesty hast thou laid upon him.",
    "hash": "862620f801a9d88e330d740ac8ecdb1865a1b5d149d5e658a216594b70692075"
  },
  {
    "id": "PSA.21.6",
    "book": "Psalms",
    "bookNum": 19,
    "bookAbbrev": "PSA",
    "chapter": 21,
    "verse": 6,
    "text": "For thou hast made him most blessed for ever: thou hast made him exceeding glad with thy countenance. {made him most...: Heb. set him to be blessings} {made him exceeding...: Heb. make him glad with joy}",
    "hash": "d420b5f2b8ef9dee700e5f87f564a56b9e1d03e807cc5743ef8a2a3774aeaa9c"
  },
  {
    "id": "PSA.21.7",
    "book": "Psalms",
    "bookNum": 19,
    "bookAbbrev": "PSA",
    "chapter": 21,
    "verse": 7,
    "text": "For the king trusteth in the LORD, and through the mercy of the most High he shall not be moved.",
    "hash": "990af0f446bb9ed55af9fcb5914e1c94c4026d982b543aa554fcd8edc0a63dfe"
  },
  {
    "id": "PSA.21.8",
    "book": "Psalms",
    "bookNum": 19,
    "bookAbbrev": "PSA",
    "chapter": 21,
    "verse": 8,
    "text": "Thine hand shall find out all thine enemies: thy right hand shall find out those that hate thee.",
    "hash": "d19ed160d2b10ee7cf3af64e62deffecd61ee53391b4371ba0fc0612c8d094d2"
  },
  {
    "id": "PSA.21.9",
    "book": "Psalms",
    "bookNum": 19,
    "bookAbbrev": "PSA",
    "chapter": 21,
    "verse": 9,
    "text": "Thou shalt make them as a fiery oven in the time of thine anger: the LORD shall swallow them up in his wrath, and the fire shall devour them.",
    "hash": "fcb4bd92d8ade7682179d65f904d2c26bbec3a5819fc33a9363c6e10668120f3"
  },
  {
    "id": "PSA.21.10",
    "book": "Psalms",
    "bookNum": 19,
    "bookAbbrev": "PSA",
    "chapter": 21,
    "verse": 10,
    "text": "Their fruit shalt thou destroy from the earth, and their seed from among the children of men.",
    "hash": "83de8354797b7aca24e828b423a2f07437405b92d388cfc3eb74cc32ad14b8c1"
  },
  {
    "id": "PSA.21.11",
    "book": "Psalms",
    "bookNum": 19,
    "bookAbbrev": "PSA",
    "chapter": 21,
    "verse": 11,
    "text": "For they intended evil against thee: they imagined a mischievous device, {which} they are not able {to perform}.",
    "hash": "995327faa350c9bc4e4a02a344107d3fee0e79e9c2952b93508b900ebd7720bd"
  },
  {
    "id": "PSA.21.12",
    "book": "Psalms",
    "bookNum": 19,
    "bookAbbrev": "PSA",
    "chapter": 21,
    "verse": 12,
    "text": "Therefore shalt thou make them turn their back, {when} thou shalt make ready {thine arrows} upon thy strings against the face of them. {shalt thou...: or, thou shalt set them as a butt} {back: Heb. shoulder}",
    "hash": "61ce801119f0ec25a987a9932af83762d1149c867022795c119496a07f0e2d3c"
  },
  {
    "id": "PSA.21.13",
    "book": "Psalms",
    "bookNum": 19,
    "bookAbbrev": "PSA",
    "chapter": 21,
    "verse": 13,
    "text": "Be thou exalted, LORD, in thine own strength: {so} will we sing and praise thy power.",
    "hash": "dad0f629b68cda5aed9da29dbd8591110940e7a697c420efd67ffdfce2d2cefa"
  }
]