[
  {
    "id": "ROM.4.1",
    "book": "Romans",
    "bookNum": 45,
    "bookAbbrev": "ROM",
    "chapter": 4,
    "verse": 1,
    "text": "What shall we say then that Abraham our father, as pertaining to the flesh, hath found?",
    "hash": "da8e347ed857d262a23b0d11303bfbacf95c742f983045793253d162defd34aa"
  },
  {
    "id": "ROM.4.2",
    "book": "Romans",
    "bookNum": 45,
    "bookAbbrev": "ROM",
    "chapter": 4,
    "verse": 2,
    "text": "For if Abraham were justified by works, he hath {whereof} to glory; but not before God.",
    "hash": "feef6128b1026a3605212a46ac063d5fc38cb12c52da2ccf32b12bbce9d5a9fc"
  },
  {
    "id": "ROM.4.3",
    "book": "Romans",
    "bookNum": 45,
    "bookAbbrev": "ROM",
    "chapter": 4,
    "verse": 3,
    "text": "For what saith the scripture? Abraham believed God, and it was counted unto him for righteousness.",
    "hash": "7646cb8d6238d4865e9057bfec598d1edc60b40fbce7cf5475fd584873563582"
  },
  {
    "id": "ROM.4.4",
    "book": "Romans",
    "bookNum": 45,
    "bookAbbrev": "ROM",
    "chapter": 4,
    "verse": 4,
    "text": "Now to him that worketh is the reward not reckoned of grace, but of debt.",
    "hash": "217b914e6db2a423fec432eae4d676389d1ff2e1f8486bc5a190463d643b5136"
  },
  {
    "id": "ROM.4.5",
    "book": "Romans",
    "bookNum": 45,
    "bookAbbrev": "ROM",
    "chapter": 4,
    "verse": 5,
    "text": "But to him that worketh not, but believeth on him that justifieth the ungodly, his faith is counted for righteousness.",
    "hash": "158f672eaaa9ed3f5ad884f6bee11622f437072289a73756f26056673f433191"
  },
  {
    "id": "ROM.4.6",
    "book": "Romans",
    "bookNum": 45,
    "bookAbbrev": "ROM",
    "chapter": 4,
    "verse": 6,
    "text": "Even as David also describeth the blessedness of the man, unto whom God imputeth righteousness without works,",
    "hash": "ce72b29cd41d031ce2f6d2d9d5e836b74a8ccd383b4f89efe5050680d91c64cd"
  },
  {
    "id": "ROM.4.7",
    "book": "Romans",
    "bookNum": 45,
    "bookAbbrev": "ROM",
    "chapter": 4,
    "verse": 7,
    "text": "{Saying}, Blessed {are} they whose iniquities are forgiven, and whose sins are covered.",
    "hash": "3ffc217c69c5f71048e3e441fda639b858ef90ac071286053b534d4239d3d187"
  },
  {
    "id": "ROM.4.8",
    "book": "Romans",
    "bookNum": 45,
    "bookAbbrev": "ROM",
    "chapter": 4,
    "verse": 8,
    "text": "Blessed {is} the man to whom the Lord will not impute sin.",
    "hash": "55a86de1d84895325393f5fb5a2646dba7c90d1025cd11cfaeb358fb7e96193d"
  },
  {
    "id": "ROM.4.9",
    "book": "Romans",
    "bookNum": 45,
    "bookAbbrev": "ROM",
    "chapter": 4,
    "verse": 9,
    "text": "{Cometh} this blessedness then upon the circumcision {only}, or upon the uncircumcision also? for we say that faith was reckoned to Abraham for righteousness.",
    "hash": "88ba57aaaa383dd2e22e46cc54b8c4956e71e7916f1739e20617a614a75fdbe8"
  },
  {
    "id": "ROM.4.10",
    "book": "Romans",
    "bookNum": 45,
    "bookAbbrev": "ROM",
    "chapter": 4,
    "verse": 10,
    "text": "How was it then reckoned? when he was in circumcision, or in uncircumcision? Not in circumcision, but in uncircumcision.",
    "hash": "717c1247a12ef43a2dbfc7165d52b076f3cf2c46745b0f8c2a56855353871b11"
  },
  {
    "id": "ROM.4.11",
    "book": "Romans",
    "bookNum": 45,
    "bookAbbrev": "ROM",
    "chapter": 4,
    "verse": 11,
    "text": "And he received the sign of circumcision, a seal of the righteousness of the faith which {he had yet} being uncircumcised: that he might be the father of all them that believe, though they be not circumcised; that righteousness might be imputed unto them also:",
    "hash": "b7f4fcdceec9d0b7515f79a0c2fde8080de2994e5facf92e15c3d436a06438cc"
  },
  {
    "id": "ROM.4.12",
    "book": "Romans",
    "bookNum": 45,
    "bookAbbrev": "ROM",
    "chapter": 4,
    "verse": 12,
    "text": "And the father of circumcision to them who are not of the circumcision only, but who also walk in the steps of that faith of our father Abraham, which {he had} being {yet} uncircumcised.",
    "hash": "9bc9892c1bfef9d8ca98c95a9891e2c274635a21df39854474114fdc531c809c"
  },
  {
    "id": "ROM.4.13",
    "book": "Romans",
    "bookNum": 45,
    "bookAbbrev": "ROM",
    "chapter": 4,
    "verse": 13,
    "text": "For the promise, that he should be the heir of the world, {was} not to Abraham, or to his seed, through the law, but through the righteousness of faith.",
    "hash": "3d4d6863219a96675f46c788279fd6078a8580053610663b5a83eacee1c9b1ae"
  },
  {
    "id": "ROM.4.14",
    "book": "Romans",
    "bookNum": 45,
    "bookAbbrev": "ROM",
    "chapter": 4,
    "verse": 14,
    "text": "For if they which are of the law {be} heirs, faith is made void, and the promise made of none effect:",
    "hash": "9138b9a270d058e48cf1e4942f6803555e918efaa2a026cf40f868f0b9642147"
  },
  {
    "id": "ROM.4.15",
    "book": "Romans",
    "bookNum": 45,
    "bookAbbrev": "ROM",
    "chapter": 4,
    "verse": 15,
    "text": "Because the law worketh wrath: for where no law is, {there is} no transgression.",
    "hash": "79c09b88e03f4b68462dbc9b1fe2e9b59ab285ffcc09e9683468772bf299e306"
  },
  {
    "id": "ROM.4.16",
    "book": "Romans",
    "bookNum": 45,
    "bookAbbrev": "ROM",
    "chapter": 4,
    "verse": 16,
    "text": "Therefore {it is} of faith, that {it might be} by grace; to the end the promise might be sure to all the seed; not to that only which is of the law, but to that also which is of the faith of Abraham; who is the father of us all,",
    "hash": "aa02ff3ae13a8f93018b97cf6832c0a0ba5c008396bf4837aca0c3b2ea435950"
  },
  {
    "id": "ROM.4.17",
    "book": "Romans",
    "bookNum": 45,
    "bookAbbrev": "ROM",
    "chapter": 4,
    "verse": 17,
    "text": "(As it is written, I have made thee a father of many nations,) before him whom he believed, {even} God, who quickeneth the dead, and calleth those things which be not as though they were. {before him: or, like unto him}",
    "hash": "73428e0af1c025ed0901de47051ff9cf33b0392ed28885af6c65c3d97d42eed5"
  },
  {
    "id": "ROM.4.18",
    "book": "Romans",
    "bookNum": 45,
    "bookAbbrev": "ROM",
    "chapter": 4,
    "verse": 18,
    "text": "Who against hope believed in hope, that he might become the father of many nations, according to that which was spoken, So shall thy seed be.",
    "hash": "fc031559bf5e62d5945c22a8afefaca464c6c969a4befba27594e2cc70b53262"
  },
  {
    "id": "ROM.4.19",
    "book": "Romans",
    "bookNum": 45,
    "bookAbbrev": "ROM",
    "chapter": 4,
    "verse": 19,
    "text": "And being not weak in faith, he considered not his own body now dead, when he was about an hundred years old, neither yet the deadness of Sara's womb:",
    "hash": "e204b33ab22d2b27b2e9fc12ac32034d8e235e09c3dc36d63e823b1ff7586b38"
  },
  {
    "id": "ROM.4.20",
    "book": "Romans",
    "bookNum": 45,
    "bookAbbrev": "ROM",
    "chapter": 4,
    "verse": 20,
    "text": "He staggered not at the promise of God through unbelief; but was strong in faith, giving glory to God;",
    "hash": "8e38844dd82cf8861497c4edd9ea7e155aa6c4966932030378537d96c9885cb6"
  },
  {
    "id": "ROM.4.21",
    "book": "Romans",
    "bookNum": 45,
    "bookAbbrev": "ROM",
    "chapter": 4,
    "verse": 21,
    "text": "And being fully persuaded that, what he had promised, he was able also to perform.",
    "hash": "2264d1970a07243a53ed1588960a5588b354b108ff756312012655107e8c099e"
  },
  {
    "id": "ROM.4.22",
    "book": "Romans",
    "bookNum": 45,
    "bookAbbrev": "ROM",
    "chapter": 4,
    "verse": 22,
    "text": "And therefore it was imputed to him for righteousness.",
    "hash": "03fdad64d3afc2a9ce35d1595000eb371d149d9049b6ac2ea8c372eaccd63ff4"
  },
  {
    "id": "ROM.4.23",
    "book": "Romans",
    "bookNum": 45,
    "bookAbbrev": "ROM",
    "chapter": 4,
    "verse": 23,
    "text": "Now it was not written for his sake alone, that it was imputed to him;",
    "hash": "fc9b5eb38ad300bb5803be5f7309cb14241b3f9c810f891972a4ca2a8c31fdf5"
  },
  {
    "id": "ROM.4.24",
    "book": "Romans",
    "bookNum": 45,
    "bookAbbrev": "ROM",
    "chapter": 4,
    "verse": 24,
    "text": "But for us also, to whom it shall be imputed, if we believe on him that raised up Jesus our Lord from the dead;",
    "hash": "1ccf57860ef1cd7129eb145198591e3a58405dfb2f1bfc3259b4f7cc77d6f08b"
  },
  {
    "id": "ROM.4.25",
    "book": "Romans",
    "bookNum": 45,
    "bookAbbrev": "ROM",
    "chapter": 4,
    "verse": 25,
    "text": "Who was delivered for our offences, and was raised again for our justification.",
    "hash": "90624ec64e0eb74f1e02e753cab487921ebb50b7aeee0a96a39c7b628483fc2e"
  }
]